ez_tess_ocr/__init__.py
ez_tess_ocr-0.0.3.data/data/tesslib/libLerc.dll
ez_tess_ocr-0.0.3.data/data/tesslib/libarchive-13.dll
ez_tess_ocr-0.0.3.data/data/tesslib/libb2-1.dll
ez_tess_ocr-0.0.3.data/data/tesslib/libbrotlicommon.dll
ez_tess_ocr-0.0.3.data/data/tesslib/libbrotlidec.dll
ez_tess_ocr-0.0.3.data/data/tesslib/libbz2-1.dll
ez_tess_ocr-0.0.3.data/data/tesslib/libcairo-2.dll
ez_tess_ocr-0.0.3.data/data/tesslib/libcrypto-3-x64.dll
ez_tess_ocr-0.0.3.data/data/tesslib/libcurl-4.dll
ez_tess_ocr-0.0.3.data/data/tesslib/libdatrie-1.dll
ez_tess_ocr-0.0.3.data/data/tesslib/libdeflate.dll
ez_tess_ocr-0.0.3.data/data/tesslib/libexpat-1.dll
ez_tess_ocr-0.0.3.data/data/tesslib/libffi-8.dll
ez_tess_ocr-0.0.3.data/data/tesslib/libfontconfig-1.dll
ez_tess_ocr-0.0.3.data/data/tesslib/libfreetype-6.dll
ez_tess_ocr-0.0.3.data/data/tesslib/libfribidi-0.dll
ez_tess_ocr-0.0.3.data/data/tesslib/libgcc_s_seh-1.dll
ez_tess_ocr-0.0.3.data/data/tesslib/libgif-7.dll
ez_tess_ocr-0.0.3.data/data/tesslib/libgio-2.0-0.dll
ez_tess_ocr-0.0.3.data/data/tesslib/libglib-2.0-0.dll
ez_tess_ocr-0.0.3.data/data/tesslib/libgmodule-2.0-0.dll
ez_tess_ocr-0.0.3.data/data/tesslib/libgobject-2.0-0.dll
ez_tess_ocr-0.0.3.data/data/tesslib/libgraphite2.dll
ez_tess_ocr-0.0.3.data/data/tesslib/libharfbuzz-0.dll
ez_tess_ocr-0.0.3.data/data/tesslib/libiconv-2.dll
ez_tess_ocr-0.0.3.data/data/tesslib/libicudt72.dll
ez_tess_ocr-0.0.3.data/data/tesslib/libicuin72.dll
ez_tess_ocr-0.0.3.data/data/tesslib/libicuuc72.dll
ez_tess_ocr-0.0.3.data/data/tesslib/libidn2-0.dll
ez_tess_ocr-0.0.3.data/data/tesslib/libintl-8.dll
ez_tess_ocr-0.0.3.data/data/tesslib/libjbig-0.dll
ez_tess_ocr-0.0.3.data/data/tesslib/libjpeg-8.dll
ez_tess_ocr-0.0.3.data/data/tesslib/libleptonica-6.dll
ez_tess_ocr-0.0.3.data/data/tesslib/liblz4.dll
ez_tess_ocr-0.0.3.data/data/tesslib/liblzma-5.dll
ez_tess_ocr-0.0.3.data/data/tesslib/libopenjp2-7.dll
ez_tess_ocr-0.0.3.data/data/tesslib/libpango-1.0-0.dll
ez_tess_ocr-0.0.3.dist-info/METADATA
ez_tess_ocr-0.0.3.dist-info/WHEEL
ez_tess_ocr-0.0.3.dist-info/top_level.txt
ez_tess_ocr-0.0.3.dist-info/RECORD
