Metadata-Version: 2.1
Name: ez-tess-ocr
Version: 0.0.3
Summary: OCR by tesseract c++ library
Home-page: https://github.com/sheauren/ez_tess_ocr
Author: Sheauren Wang
Author-email: sheauren@gmail.com
Classifier: Programming Language :: Python :: 3.5
Classifier: License :: OSI Approved :: MIT License
Requires-Python: >=3.5
